WhoColor/__init__.py
WhoColor/handler.py
WhoColor/parser.py
WhoColor/special_markups.py
WhoColor/utils.py
WhoColor/static/whocolor/images/ArticleSearch.svg
WhoColor/static/whocolor/images/Article_icon.svg
WhoColor/static/whocolor/images/Clear_icon.svg
WhoColor/static/whocolor/images/Speechbubbles_icon.svg
WhoColor/static/whocolor/images/Speechbubbles_icon_green.svg
WhoColor/static/whocolor/images/UserAvatar.svg
WhoColor/static/whocolor/images/ajax-loader.gif
WhoColor/static/whocolor/scripts/moment-with-locales.js
WhoColor/tests/__init__.py
WhoColor/tests/prepare_test_data.py
WhoColor/tests/profile_parser.py
WhoColor/tests/test_parser.py
WhoColor/tests/test_utils.py
WhoColor-1.0.1.dist-info/LICENSE.txt
WhoColor-1.0.1.dist-info/METADATA
WhoColor-1.0.1.dist-info/WHEEL
WhoColor-1.0.1.dist-info/top_level.txt
WhoColor-1.0.1.dist-info/RECORD
