Metadata-Version: 2.1
Name: WhoColor
Version: 1.0.1
Summary: An algorithm to create an on-demand color-markup of the original authors of the text of any article on the (english) Wikipedia.
Home-page: https://github.com/wikiwho/whoCOLOR
Author: UNKNOWN
Author-email: UNKNOWN
License: MIT
Keywords: wikipedia revision token authorship color visualization
Platform: UNKNOWN
Classifier: License :: OSI Approved :: MIT License
Classifier: Programming Language :: Python :: 2.7
Classifier: Programming Language :: Python :: 3
Classifier: Programming Language :: Python :: 3.3
Classifier: Programming Language :: Python :: 3.4
Classifier: Programming Language :: Python :: 3.5
Requires-Dist: requests
Requires-Dist: python-dateutil
